odoo/addons/shopinvader_category_image_for_product/README.rst
odoo/addons/shopinvader_category_image_for_product/__init__.py
odoo/addons/shopinvader_category_image_for_product/__manifest__.py
odoo/addons/shopinvader_category_image_for_product/data/ir_export.xml
odoo/addons/shopinvader_category_image_for_product/i18n/shopinvader_category_image_for_product.pot
odoo/addons/shopinvader_category_image_for_product/models/__init__.py
odoo/addons/shopinvader_category_image_for_product/models/shopinvader_variant.py
odoo/addons/shopinvader_category_image_for_product/readme/CONTRIBUTORS.rst
odoo/addons/shopinvader_category_image_for_product/readme/DESCRIPTION.rst
odoo/addons/shopinvader_category_image_for_product/static/description/index.html
odoo14_addon_shopinvader_category_image_for_product-14.0.1.0.1.dist-info/METADATA
odoo14_addon_shopinvader_category_image_for_product-14.0.1.0.1.dist-info/WHEEL
odoo14_addon_shopinvader_category_image_for_product-14.0.1.0.1.dist-info/top_level.txt
odoo14_addon_shopinvader_category_image_for_product-14.0.1.0.1.dist-info/RECORD
