Metadata-Version: 2.1
Name: odoo14-addon-shopinvader-category-image-for-product
Version: 14.0.1.0.1
Summary: Shopinvader Display category image for product
Home-page: https://github.com/shopinvader/odoo-shopinvader
Author: ACSONE SA/NV
License: AGPL-3
Platform: UNKNOWN
Classifier: Programming Language :: Python
Classifier: Framework :: Odoo
Classifier: License :: OSI Approved :: GNU Affero General Public License v3
Requires-Python: >=3.6
Requires-Dist: odoo14-addon-shopinvader
Requires-Dist: odoo14-addon-shopinvader-image
Requires-Dist: odoo14-addon-shopinvader-search-engine
Requires-Dist: odoo (<14.1dev,>=14.0a)
